pyhinavrophonetic/__init__.py
pyhinavrophonetic/config.py
pyhinavrophonetic/hinavro.py
pyhinavrophonetic/resources/__init__.py
pyhinavrophonetic/resources/avrodict.json
pyhinavrophonetic/utils/__init__.py
pyhinavrophonetic/utils/count.py
pyhinavrophonetic/utils/validate.py
pyhinavrophonetic-2.0.2.dist-info/LICENSE
pyhinavrophonetic-2.0.2.dist-info/METADATA
pyhinavrophonetic-2.0.2.dist-info/WHEEL
pyhinavrophonetic-2.0.2.dist-info/top_level.txt
pyhinavrophonetic-2.0.2.dist-info/RECORD
