Metadata-Version: 2.1
Name: pyhinavrophonetic
Version: 2.0.2
Summary: Python implementation to convert phonetic to hindi
Home-page: https://bitbucket.org/SubrataSarkar32/pyhinavrophonetic/
Author: Subrata Sarkar
Author-email: subrotosarkar32@gmail.com
License: GNU GPL v3 or later
Platform: UNKNOWN
Classifier: Development Status :: 3 - Alpha
Classifier: Intended Audience :: Developers
Classifier: License :: OSI Approved :: GNU General Public License v3 or later (GPLv3+)
Classifier: Operating System :: OS Independent
Classifier: Programming Language :: Python :: 3
